setup.py
miplant/__init__.py
miplant/miplant.py
miplant.egg-info/PKG-INFO
miplant.egg-info/SOURCES.txt
miplant.egg-info/dependency_links.txt
miplant.egg-info/requires.txt
miplant.egg-info/top_level.txt