Metadata-Version: 1.0
Name: miplant
Version: 0.0.1
Summary: A library for reading cheap plant monitoring sensors manufactured by Xiaomi.
Home-page: https://github.com/kipe/miplant
Author: Kimmo Huoman
Author-email: kipenroskaposti@gmail.com
License: UNKNOWN
Platform: UNKNOWN
